LICENSE.txt
MANIFEST.in
setup.py
examples/demo.py
examples/demo_hiredis.py
examples/pubsub.py
txredis/__init__.py
txredis/client.py
txredis/exceptions.py
txredis/protocol.py
txredis/testing.py
txredis.egg-info/PKG-INFO
txredis.egg-info/SOURCES.txt
txredis.egg-info/dependency_links.txt
txredis.egg-info/top_level.txt
txredis/tests/__init__.py
txredis/tests/test_client.py
txredis/tests/test_hiredis.py